vigieaupy/__init__.py
vigieaupy/api.py
vigieaupy/auth.py
vigieaupy/consts.py
vigieaupy/exceptions.py
vigieaupy-1.0.0.dist-info/licenses/LICENSE
vigieaupy-1.0.0.dist-info/METADATA
vigieaupy-1.0.0.dist-info/WHEEL
vigieaupy-1.0.0.dist-info/top_level.txt
vigieaupy-1.0.0.dist-info/RECORD
